{
  "protocol_version" : "0.0.6",
  "configuration" : {
    "version" : "(6.13.0) (explicit/664fdcba172)",
    "tlc" : "__thread",
    "sigsgev" : "normal",
    "notifications" : "kqueue",
    "architecture" : "arm64",
    "disabled_features" : "com,shared_perfcounters",
    "smallconfig" : "disabled",
    "bigarrays" : "disabled",
    "softdebug" : "enabled",
    "interpreter" : "enabled",
    "llvm_support" : "disabled",
    "suspend" : "preemptive"
  },
  "memory" : {
    "Resident Size" : "472317952",
    "Virtual Size" : "422143754240",
    "minor_gc_time" : "0",
    "major_gc_time" : "6270160",
    "minor_gc_count" : "0",
    "major_gc_count" : "119",
    "major_gc_time_concurrent" : "0"
 },
  "threads" : [
 {
    "is_managed" : false,
    "offset_free_hash" : "0x0",
    "offset_rich_hash" : "0x0",
    "crashed" : false,
    "native_thread_id" : "0x284cc3000",
    "thread_info_addr" : "0x2901ef600",
    "thread_name" : "Thread Pool Worker",
    "ctx" : {
      "IP" : "0x1afa6e904",
      "SP" : "0x284cc2db0",
      "BP" : "0x284cc2e50"
  },
    "unmanaged_frames" : [
  {
      "is_managed" : "false",
      "native_address" : "0x17d701c4c",
      "native_offset" : "0x00000"
   }
,
  {
      "is_managed" : "false",
      "native_address" : "0x17d838788",
      "native_offset" : "0x00000"
   }
,
  {
      "is_managed" : "false",
      "native_address" : "0x17d838ae4",
      "native_offset" : "0x00000"
   }
,
  {
      "is_managed" : "false",
      "native_address" : "0x17d8388ac",
      "native_offset" : "0x00000"
   }
,
  {
      "is_managed" : "false",
      "native_address" : "0x17d742bd4",
      "native_offset" : "0x00000"
   }
,
  {
      "is_managed" : "false",
      "native_address" : "0x1afac34a4",
      "native_offset" : "0x00000"
   }
,
  {
      "is_managed" : "false",
      "native_address" : "0x17d790c70",
      "native_offset" : "0x00000"
   }
,
  {
      "is_managed" : "false",
      "native_address" : "0x17d8394f4",
      "native_offset" : "0x00000"
   }
,
  {
      "is_managed" : "false",
      "native_address" : "0x17d8393a0",
      "native_offset" : "0x00000"
   }
,
  {
      "is_managed" : "false",
      "native_address" : "0x17d8b8cb0",
      "native_offset" : "0x00000"
   }
,
  {
      "is_managed" : "false",
      "native_address" : "0x17d8b8c38",
      "native_offset" : "0x00000"
   }
,
  {
      "is_managed" : "false",
      "native_address" : "0x1afaac26c",
      "native_offset" : "0x00000"
   }
,
  {
      "is_managed" : "false",
      "native_address" : "0x1afaa708c",
      "native_offset" : "0x00000"
   }

  ]
 },
 {
    "is_managed" : false,
    "offset_free_hash" : "0x0",
    "offset_rich_hash" : "0x0",
    "crashed" : false,
    "native_thread_id" : "0x2cea07000",
    "thread_info_addr" : "0x12d34e600",
    "thread_name" : "Thread Pool Worker",
    "ctx" : {
      "IP" : "0x1afa6e904",
      "SP" : "0x2cea06db0",
      "BP" : "0x2cea06e50"
  },
    "unmanaged_frames" : [
  {
      "is_managed" : "false",
      "native_address" : "0x17d701c4c",
      "native_offset" : "0x00000"
   }
,
  {
      "is_managed" : "false",
      "native_address" : "0x17d838788",
      "native_offset" : "0x00000"
   }
,
  {
      "is_managed" : "false",
      "native_address" : "0x17d838ae4",
      "native_offset" : "0x00000"
   }
,
  {
      "is_managed" : "false",
      "native_address" : "0x17d8388ac",
      "native_offset" : "0x00000"
   }
,
  {
      "is_managed" : "false",
      "native_address" : "0x17d742bd4",
      "native_offset" : "0x00000"
   }
,
  {
      "is_managed" : "false",
      "native_address" : "0x1afac34a4",
      "native_offset" : "0x00000"
   }
,
  {
      "is_managed" : "false",
      "native_address" : "0x17d790c70",
      "native_offset" : "0x00000"
   }
,
  {
      "is_managed" : "false",
      "native_address" : "0x17d8394f4",
      "native_offset" : "0x00000"
   }
,
  {
      "is_managed" : "false",
      "native_address" : "0x17d8393a0",
      "native_offset" : "0x00000"
   }
,
  {
      "is_managed" : "false",
      "native_address" : "0x17d8b8cb0",
      "native_offset" : "0x00000"
   }
,
  {
      "is_managed" : "false",
      "native_address" : "0x17d8b8c38",
      "native_offset" : "0x00000"
   }
,
  {
      "is_managed" : "false",
      "native_address" : "0x1afaac26c",
      "native_offset" : "0x00000"
   }
,
  {
      "is_managed" : "false",
      "native_address" : "0x1afaa708c",
      "native_offset" : "0x00000"
   }

  ]
 },
 {
    "is_managed" : false,
    "offset_free_hash" : "0x0",
    "offset_rich_hash" : "0x0",
    "crashed" : false,
    "native_thread_id" : "0x2d09b7000",
    "thread_info_addr" : "0x113fef000",
    "thread_name" : "Thread Pool Worker",
    "ctx" : {
      "IP" : "0x1afa6e904",
      "SP" : "0x2d09b6db0",
      "BP" : "0x2d09b6e50"
  },
    "unmanaged_frames" : [
  {
      "is_managed" : "false",
      "native_address" : "0x17d701c4c",
      "native_offset" : "0x00000"
   }
,
  {
      "is_managed" : "false",
      "native_address" : "0x17d838788",
      "native_offset" : "0x00000"
   }
,
  {
      "is_managed" : "false",
      "native_address" : "0x17d838ae4",
      "native_offset" : "0x00000"
   }
,
  {
      "is_managed" : "false",
      "native_address" : "0x17d8388ac",
      "native_offset" : "0x00000"
   }
,
  {
      "is_managed" : "false",
      "native_address" : "0x17d742bd4",
      "native_offset" : "0x00000"
   }
,
  {
      "is_managed" : "false",
      "native_address" : "0x1afac34a4",
      "native_offset" : "0x00000"
   }
,
  {
      "is_managed" : "false",
      "native_address" : "0x17d790c70",
      "native_offset" : "0x00000"
   }
,
  {
      "is_managed" : "false",
      "native_address" : "0x17d8394f4",
      "native_offset" : "0x00000"
   }
,
  {
      "is_managed" : "false",
      "native_address" : "0x17d8393a0",
      "native_offset" : "0x00000"
   }
,
  {
      "is_managed" : "false",
      "native_address" : "0x17d8b8cb0",
      "native_offset" : "0x00000"
   }
,
  {
      "is_managed" : "false",
      "native_address" : "0x17d8b8c38",
      "native_offset" : "0x00000"
   }
,
  {
      "is_managed" : "false",
      "native_address" : "0x1afaac26c",
      "native_offset" : "0x00000"
   }
,
  {
      "is_managed" : "false",
      "native_address" : "0x1afaa708c",
      "native_offset" : "0x00000"
   }

  ]
 },
 {
    "is_managed" : false,
    "offset_free_hash" : "0x0",
    "offset_rich_hash" : "0x0",
    "crashed" : false,
    "native_thread_id" : "0x2893bf000",
    "thread_info_addr" : "0x29183d800",
    "thread_name" : "tid_1b393",
    "ctx" : {
      "IP" : "0x1afa72270",
      "SP" : "0x2893bec20",
      "BP" : "0x2893becb0"
  },
    "unmanaged_frames" : [
  {
      "is_managed" : "false",
      "native_address" : "0x17d701c4c",
      "native_offset" : "0x00000"
   }
,
  {
      "is_managed" : "false",
      "native_address" : "0x17d838788",
      "native_offset" : "0x00000"
   }
,
  {
      "is_managed" : "false",
      "native_address" : "0x17d838ae4",
      "native_offset" : "0x00000"
   }
,
  {
      "is_managed" : "false",
      "native_address" : "0x17d8388ac",
      "native_offset" : "0x00000"
   }
,
  {
      "is_managed" : "false",
      "native_address" : "0x17d742bd4",
      "native_offset" : "0x00000"
   }
,
  {
      "is_managed" : "false",
      "native_address" : "0x1afac34a4",
      "native_offset" : "0x00000"
   }
,
  {
      "is_managed" : "false",
      "native_address" : "0x1afaac868",
      "native_offset" : "0x00000"
   }
,
  {
      "is_managed" : "false",
      "native_address" : "0x17d887e08",
      "native_offset" : "0x00000"
   }
,
  {
      "is_managed" : "false",
      "native_address" : "0x17d891ae4",
      "native_offset" : "0x00000"
   }
,
  {
      "is_managed" : "false",
      "native_address" : "0x17d790478",
      "native_offset" : "0x00000"
   }
,
  {
      "is_managed" : "false",
      "native_address" : "0x17d8394f4",
      "native_offset" : "0x00000"
   }
,
  {
      "is_managed" : "false",
      "native_address" : "0x17d8393a0",
      "native_offset" : "0x00000"
   }
,
  {
      "is_managed" : "false",
      "native_address" : "0x17d8b8cb0",
      "native_offset" : "0x00000"
   }
,
  {
      "is_managed" : "false",
      "native_address" : "0x17d8b8c38",
      "native_offset" : "0x00000"
   }
,
  {
      "is_managed" : "false",
      "native_address" : "0x1afaac26c",
      "native_offset" : "0x00000"
   }
,
  {
      "is_managed" : "false",
      "native_address" : "0x1afaa708c",
      "native_offset" : "0x00000"
   }

  ]
 },
 {
    "is_managed" : false,
    "offset_free_hash" : "0x0",
    "offset_rich_hash" : "0x0",
    "crashed" : false,
    "native_thread_id" : "0x28954b000",
    "thread_info_addr" : "0x2d4f18e00",
    "thread_name" : "tid_339cf",
    "ctx" : {
      "IP" : "0x1afa6e8ec",
      "SP" : "0x28954ad80",
      "BP" : "0x28954ad90"
  },
    "unmanaged_frames" : [
  {
      "is_managed" : "false",
      "native_address" : "0x17d701c4c",
      "native_offset" : "0x00000"
   }
,
  {
      "is_managed" : "false",
      "native_address" : "0x17d838788",
      "native_offset" : "0x00000"
   }
,
  {
      "is_managed" : "false",
      "native_address" : "0x17d838ae4",
      "native_offset" : "0x00000"
   }
,
  {
      "is_managed" : "false",
      "native_address" : "0x17d8388ac",
      "native_offset" : "0x00000"
   }
,
  {
      "is_managed" : "false",
      "native_address" : "0x17d742bd4",
      "native_offset" : "0x00000"
   }
,
  {
      "is_managed" : "false",
      "native_address" : "0x1afac34a4",
      "native_offset" : "0x00000"
   }
,
  {
      "is_managed" : "false",
      "native_address" : "0x1af8e8750",
      "native_offset" : "0x00000"
   }
,
  {
      "is_managed" : "false",
      "native_address" : "0x1af8e8df8",
      "native_offset" : "0x00000"
   }
,
  {
      "is_managed" : "false",
      "native_address" : "0x10764592c",
      "native_offset" : "0x00000"
   }
,
  {
      "is_managed" : "false",
      "native_address" : "0x10517bd70",
      "native_offset" : "0x00000"
   }
,
  {
      "is_managed" : "false",
      "native_address" : "0x10552848c",
      "native_offset" : "0x00000"
   }
,
  {
      "is_managed" : "false",
      "native_address" : "0x105528428",
      "native_offset" : "0x00000"
   }
,
  {
      "is_managed" : "false",
      "native_address" : "0x1056b04d8",
      "native_offset" : "0x00000"
   }
,
  {
      "is_managed" : "false",
      "native_address" : "0x1afaac26c",
      "native_offset" : "0x00000"
   }
,
  {
      "is_managed" : "false",
      "native_address" : "0x1afaa708c",
      "native_offset" : "0x00000"
   }

  ]
 },
 {
    "is_managed" : false,
    "offset_free_hash" : "0x0",
    "offset_rich_hash" : "0x0",
    "crashed" : false,
    "native_thread_id" : "0x28dba3000",
    "thread_info_addr" : "0x291aa6800",
    "thread_name" : "Thread Pool Worker",
    "ctx" : {
      "IP" : "0x1afa6e904",
      "SP" : "0x28dba2db0",
      "BP" : "0x28dba2e50"
  },
    "unmanaged_frames" : [
  {
      "is_managed" : "false",
      "native_address" : "0x17d701c4c",
      "native_offset" : "0x00000"
   }
,
  {
      "is_managed" : "false",
      "native_address" : "0x17d838788",
      "native_offset" : "0x00000"
   }
,
  {
      "is_managed" : "false",
      "native_address" : "0x17d838ae4",
      "native_offset" : "0x00000"
   }
,
  {
      "is_managed" : "false",
      "native_address" : "0x17d8388ac",
      "native_offset" : "0x00000"
   }
,
  {
      "is_managed" : "false",
      "native_address" : "0x17d742bd4",
      "native_offset" : "0x00000"
   }
,
  {
      "is_managed" : "false",
      "native_address" : "0x1afac34a4",
      "native_offset" : "0x00000"
   }
,
  {
      "is_managed" : "false",
      "native_address" : "0x17d790c70",
      "native_offset" : "0x00000"
   }
,
  {
      "is_managed" : "false",
      "native_address" : "0x17d8394f4",
      "native_offset" : "0x00000"
   }
,
  {
      "is_managed" : "false",
      "native_address" : "0x17d8393a0",
      "native_offset" : "0x00000"
   }
,
  {
      "is_managed" : "false",
      "native_address" : "0x17d8b8cb0",
      "native_offset" : "0x00000"
   }
,
  {
      "is_managed" : "false",
      "native_address" : "0x17d8b8c38",
      "native_offset" : "0x00000"
   }
,
  {
      "is_managed" : "false",
      "native_address" : "0x1afaac26c",
      "native_offset" : "0x00000"
   }
,
  {
      "is_managed" : "false",
      "native_address" : "0x1afaa708c",
      "native_offset" : "0x00000"
   }

  ]
 },
 {
    "is_managed" : false,
    "offset_free_hash" : "0x0",
    "offset_rich_hash" : "0x0",
    "crashed" : false,
    "native_thread_id" : "0x28b903000",
    "thread_info_addr" : "0x29c3b2400",
    "thread_name" : "Thread Pool Worker",
    "ctx" : {
      "IP" : "0x1afa6e904",
      "SP" : "0x28b902db0",
      "BP" : "0x28b902e50"
  },
    "unmanaged_frames" : [
  {
      "is_managed" : "false",
      "native_address" : "0x17d701c4c",
      "native_offset" : "0x00000"
   }
,
  {
      "is_managed" : "false",
      "native_address" : "0x17d838788",
      "native_offset" : "0x00000"
   }
,
  {
      "is_managed" : "false",
      "native_address" : "0x17d838ae4",
      "native_offset" : "0x00000"
   }
,
  {
      "is_managed" : "false",
      "native_address" : "0x17d8388ac",
      "native_offset" : "0x00000"
   }
,
  {
      "is_managed" : "false",
      "native_address" : "0x17d742bd4",
      "native_offset" : "0x00000"
   }
,
  {
      "is_managed" : "false",
      "native_address" : "0x1afac34a4",
      "native_offset" : "0x00000"
   }
,
  {
      "is_managed" : "false",
      "native_address" : "0x17d790c70",
      "native_offset" : "0x00000"
   }
,
  {
      "is_managed" : "false",
      "native_address" : "0x17d8394f4",
      "native_offset" : "0x00000"
   }
,
  {
      "is_managed" : "false",
      "native_address" : "0x17d8393a0",
      "native_offset" : "0x00000"
   }
,
  {
      "is_managed" : "false",
      "native_address" : "0x17d8b8cb0",
      "native_offset" : "0x00000"
   }
,
  {
      "is_managed" : "false",
      "native_address" : "0x17d8b8c38",
      "native_offset" : "0x00000"
   }
,
  {
      "is_managed" : "false",
      "native_address" : "0x1afaac26c",
      "native_offset" : "0x00000"
   }
,
  {
      "is_managed" : "false",
      "native_address" : "0x1afaa708c",
      "native_offset" : "0x00000"
   }

  ]
 },
 {
    "is_managed" : false,
    "offset_free_hash" : "0x0",
    "offset_rich_hash" : "0x0",
    "crashed" : false,
    "native_thread_id" : "0x283f4f000",
    "thread_info_addr" : "0x287954e00",
    "thread_name" : "Thread Pool Worker",
    "ctx" : {
      "IP" : "0x1afa6e904",
      "SP" : "0x283f4edb0",
      "BP" : "0x283f4ee50"
  },
    "unmanaged_frames" : [
  {
      "is_managed" : "false",
      "native_address" : "0x17d701c4c",
      "native_offset" : "0x00000"
   }
,
  {
      "is_managed" : "false",
      "native_address" : "0x17d838788",
      "native_offset" : "0x00000"
   }
,
  {
      "is_managed" : "false",
      "native_address" : "0x17d838ae4",
      "native_offset" : "0x00000"
   }
,
  {
      "is_managed" : "false",
      "native_address" : "0x17d8388ac",
      "native_offset" : "0x00000"
   }
,
  {
      "is_managed" : "false",
      "native_address" : "0x17d742bd4",
      "native_offset" : "0x00000"
   }
,
  {
      "is_managed" : "false",
      "native_address" : "0x1afac34a4",
      "native_offset" : "0x00000"
   }
,
  {
      "is_managed" : "false",
      "native_address" : "0x17d790c70",
      "native_offset" : "0x00000"
   }
,
  {
      "is_managed" : "false",
      "native_address" : "0x17d8394f4",
      "native_offset" : "0x00000"
   }
,
  {
      "is_managed" : "false",
      "native_address" : "0x17d8393a0",
      "native_offset" : "0x00000"
   }
,
  {
      "is_managed" : "false",
      "native_address" : "0x17d8b8cb0",
      "native_offset" : "0x00000"
   }
,
  {
      "is_managed" : "false",
      "native_address" : "0x17d8b8c38",
      "native_offset" : "0x00000"
   }
,
  {
      "is_managed" : "false",
      "native_address" : "0x1afaac26c",
      "native_offset" : "0x00000"
   }
,
  {
      "is_managed" : "false",
      "native_address" : "0x1afaa708c",
      "native_offset" : "0x00000"
   }

  ]
 },
 {
    "is_managed" : false,
    "offset_free_hash" : "0x0",
    "offset_rich_hash" : "0x0",
    "crashed" : false,
    "native_thread_id" : "0x28d207000",
    "thread_info_addr" : "0x291aa6000",
    "thread_name" : "Thread Pool Worker",
    "ctx" : {
      "IP" : "0x1afa6e904",
      "SP" : "0x28d206db0",
      "BP" : "0x28d206e50"
  },
    "unmanaged_frames" : [
  {
      "is_managed" : "false",
      "native_address" : "0x17d701c4c",
      "native_offset" : "0x00000"
   }
,
  {
      "is_managed" : "false",
      "native_address" : "0x17d838788",
      "native_offset" : "0x00000"
   }
,
  {
      "is_managed" : "false",
      "native_address" : "0x17d838ae4",
      "native_offset" : "0x00000"
   }
,
  {
      "is_managed" : "false",
      "native_address" : "0x17d8388ac",
      "native_offset" : "0x00000"
   }
,
  {
      "is_managed" : "false",
      "native_address" : "0x17d742bd4",
      "native_offset" : "0x00000"
   }
,
  {
      "is_managed" : "false",
      "native_address" : "0x1afac34a4",
      "native_offset" : "0x00000"
   }
,
  {
      "is_managed" : "false",
      "native_address" : "0x17d790c70",
      "native_offset" : "0x00000"
   }
,
  {
      "is_managed" : "false",
      "native_address" : "0x17d8394f4",
      "native_offset" : "0x00000"
   }
,
  {
      "is_managed" : "false",
      "native_address" : "0x17d8393a0",
      "native_offset" : "0x00000"
   }
,
  {
      "is_managed" : "false",
      "native_address" : "0x17d8b8cb0",
      "native_offset" : "0x00000"
   }
,
  {
      "is_managed" : "false",
      "native_address" : "0x17d8b8c38",
      "native_offset" : "0x00000"
   }
,
  {
      "is_managed" : "false",
      "native_address" : "0x1afaac26c",
      "native_offset" : "0x00000"
   }
,
  {
      "is_managed" : "false",
      "native_address" : "0x1afaa708c",
      "native_offset" : "0x00000"
   }

  ]
 },
 {
    "is_managed" : false,
    "offset_free_hash" : "0x0",
    "offset_rich_hash" : "0x0",
    "crashed" : false,
    "native_thread_id" : "0x2cf487000",
    "thread_info_addr" : "0x113fff200",
    "thread_name" : "Thread Pool Worker",
    "ctx" : {
      "IP" : "0x1afa6e904",
      "SP" : "0x2cf486db0",
      "BP" : "0x2cf486e50"
  },
    "unmanaged_frames" : [
  {
      "is_managed" : "false",
      "native_address" : "0x17d701c4c",
      "native_offset" : "0x00000"
   }
,
  {
      "is_managed" : "false",
      "native_address" : "0x17d838788",
      "native_offset" : "0x00000"
   }
,
  {
      "is_managed" : "false",
      "native_address" : "0x17d838ae4",
      "native_offset" : "0x00000"
   }
,
  {
      "is_managed" : "false",
      "native_address" : "0x17d8388ac",
      "native_offset" : "0x00000"
   }
,
  {
      "is_managed" : "false",
      "native_address" : "0x17d742bd4",
      "native_offset" : "0x00000"
   }
,
  {
      "is_managed" : "false",
      "native_address" : "0x1afac34a4",
      "native_offset" : "0x00000"
   }
,
  {
      "is_managed" : "false",
      "native_address" : "0x17d790c70",
      "native_offset" : "0x00000"
   }
,
  {
      "is_managed" : "false",
      "native_address" : "0x17d8394f4",
      "native_offset" : "0x00000"
   }
,
  {
      "is_managed" : "false",
      "native_address" : "0x17d8393a0",
      "native_offset" : "0x00000"
   }
,
  {
      "is_managed" : "false",
      "native_address" : "0x17d8b8cb0",
      "native_offset" : "0x00000"
   }
,
  {
      "is_managed" : "false",
      "native_address" : "0x17d8b8c38",
      "native_offset" : "0x00000"
   }
,
  {
      "is_managed" : "false",
      "native_address" : "0x1afaac26c",
      "native_offset" : "0x00000"
   }
,
  {
      "is_managed" : "false",
      "native_address" : "0x1afaa708c",
      "native_offset" : "0x00000"
   }

  ]
 },
 {
    "is_managed" : false,
    "offset_free_hash" : "0x0",
    "offset_rich_hash" : "0x0",
    "crashed" : false,
    "native_thread_id" : "0x2bb4af000",
    "thread_info_addr" : "0x112408200",
    "thread_name" : "Thread Pool Worker",
    "ctx" : {
      "IP" : "0x1afa6e904",
      "SP" : "0x2bb4aedb0",
      "BP" : "0x2bb4aee50"
  },
    "unmanaged_frames" : [
  {
      "is_managed" : "false",
      "native_address" : "0x17d701c4c",
      "native_offset" : "0x00000"
   }
,
  {
      "is_managed" : "false",
      "native_address" : "0x17d838788",
      "native_offset" : "0x00000"
   }
,
  {
      "is_managed" : "false",
      "native_address" : "0x17d838ae4",
      "native_offset" : "0x00000"
   }
,
  {
      "is_managed" : "false",
      "native_address" : "0x17d8388ac",
      "native_offset" : "0x00000"
   }
,
  {
      "is_managed" : "false",
      "native_address" : "0x17d742bd4",
      "native_offset" : "0x00000"
   }
,
  {
      "is_managed" : "false",
      "native_address" : "0x1afac34a4",
      "native_offset" : "0x00000"
   }
,
  {
      "is_managed" : "false",
      "native_address" : "0x17d790c70",
      "native_offset" : "0x00000"
   }
,
  {
      "is_managed" : "false",
      "native_address" : "0x17d8394f4",
      "native_offset" : "0x00000"
   }
,
  {
      "is_managed" : "false",
      "native_address" : "0x17d8393a0",
      "native_offset" : "0x00000"
   }
,
  {
      "is_managed" : "false",
      "native_address" : "0x17d8b8cb0",
      "native_offset" : "0x00000"
   }
,
  {
      "is_managed" : "false",
      "native_address" : "0x17d8b8c38",
      "native_offset" : "0x00000"
   }
,
  {
      "is_managed" : "false",
      "native_address" : "0x1afaac26c",
      "native_offset" : "0x00000"
   }
,
  {
      "is_managed" : "false",
      "native_address" : "0x1afaa708c",
      "native_offset" : "0x00000"
   }

  ]
 },
 {
    "is_managed" : false,
    "offset_free_hash" : "0x0",
    "offset_rich_hash" : "0x0",
    "crashed" : false,
    "native_thread_id" : "0x2d05e7000",
    "thread_info_addr" : "0x12e27fe00",
    "thread_name" : "Thread Pool Worker",
    "ctx" : {
      "IP" : "0x1afa6e904",
      "SP" : "0x2d05e6db0",
      "BP" : "0x2d05e6e50"
  },
    "unmanaged_frames" : [
  {
      "is_managed" : "false",
      "native_address" : "0x17d701c4c",
      "native_offset" : "0x00000"
   }
,
  {
      "is_managed" : "false",
      "native_address" : "0x17d838788",
      "native_offset" : "0x00000"
   }
,
  {
      "is_managed" : "false",
      "native_address" : "0x17d838ae4",
      "native_offset" : "0x00000"
   }
,
  {
      "is_managed" : "false",
      "native_address" : "0x17d8388ac",
      "native_offset" : "0x00000"
   }
,
  {
      "is_managed" : "false",
      "native_address" : "0x17d742bd4",
      "native_offset" : "0x00000"
   }
,
  {
      "is_managed" : "false",
      "native_address" : "0x1afac34a4",
      "native_offset" : "0x00000"
   }
,
  {
      "is_managed" : "false",
      "native_address" : "0x17d790c70",
      "native_offset" : "0x00000"
   }
,
  {
      "is_managed" : "false",
      "native_address" : "0x17d8394f4",
      "native_offset" : "0x00000"
   }
,
  {
      "is_managed" : "false",
      "native_address" : "0x17d8393a0",
      "native_offset" : "0x00000"
   }
,
  {
      "is_managed" : "false",
      "native_address" : "0x17d8b8cb0",
      "native_offset" : "0x00000"
   }
,
  {
      "is_managed" : "false",
      "native_address" : "0x17d8b8c38",
      "native_offset" : "0x00000"
   }
,
  {
      "is_managed" : "false",
      "native_address" : "0x1afaac26c",
      "native_offset" : "0x00000"
   }
,
  {
      "is_managed" : "false",
      "native_address" : "0x1afaa708c",
      "native_offset" : "0x00000"
   }

  ]
 },
 {
    "is_managed" : false,
    "offset_free_hash" : "0x0",
    "offset_rich_hash" : "0x0",
    "crashed" : false,
    "native_thread_id" : "0x2bf2d7000",
    "thread_info_addr" : "0x12e442200",
    "thread_name" : "Thread Pool Worker",
    "ctx" : {
      "IP" : "0x1afa6e904",
      "SP" : "0x2bf2d6db0",
      "BP" : "0x2bf2d6e50"
  },
    "unmanaged_frames" : [
  {
      "is_managed" : "false",
      "native_address" : "0x17d701c4c",
      "native_offset" : "0x00000"
   }
,
  {
      "is_managed" : "false",
      "native_address" : "0x17d838788",
      "native_offset" : "0x00000"
   }
,
  {
      "is_managed" : "false",
      "native_address" : "0x17d838ae4",
      "native_offset" : "0x00000"
   }
,
  {
      "is_managed" : "false",
      "native_address" : "0x17d8388ac",
      "native_offset" : "0x00000"
   }
,
  {
      "is_managed" : "false",
      "native_address" : "0x17d742bd4",
      "native_offset" : "0x00000"
   }
,
  {
      "is_managed" : "false",
      "native_address" : "0x1afac34a4",
      "native_offset" : "0x00000"
   }
,
  {
      "is_managed" : "false",
      "native_address" : "0x17d790c70",
      "native_offset" : "0x00000"
   }
,
  {
      "is_managed" : "false",
      "native_address" : "0x17d8394f4",
      "native_offset" : "0x00000"
   }
,
  {
      "is_managed" : "false",
      "native_address" : "0x17d8393a0",
      "native_offset" : "0x00000"
   }
,
  {
      "is_managed" : "false",
      "native_address" : "0x17d8b8cb0",
      "native_offset" : "0x00000"
   }
,
  {
      "is_managed" : "false",
      "native_address" : "0x17d8b8c38",
      "native_offset" : "0x00000"
   }
,
  {
      "is_managed" : "false",
      "native_address" : "0x1afaac26c",
      "native_offset" : "0x00000"
   }
,
  {
      "is_managed" : "false",
      "native_address" : "0x1afaa708c",
      "native_offset" : "0x00000"
   }

  ]
 },
 {
    "is_managed" : false,
    "offset_free_hash" : "0x0",
    "offset_rich_hash" : "0x0",
    "crashed" : false,
    "native_thread_id" : "0x282c93000",
    "thread_info_addr" : "0x2901ace00",
    "thread_name" : "Thread Pool Worker",
    "ctx" : {
      "IP" : "0x1afa6e904",
      "SP" : "0x282c92db0",
      "BP" : "0x282c92e50"
  },
    "unmanaged_frames" : [
  {
      "is_managed" : "false",
      "native_address" : "0x17d701c4c",
      "native_offset" : "0x00000"
   }
,
  {
      "is_managed" : "false",
      "native_address" : "0x17d838788",
      "native_offset" : "0x00000"
   }
,
  {
      "is_managed" : "false",
      "native_address" : "0x17d838ae4",
      "native_offset" : "0x00000"
   }
,
  {
      "is_managed" : "false",
      "native_address" : "0x17d8388ac",
      "native_offset" : "0x00000"
   }
,
  {
      "is_managed" : "false",
      "native_address" : "0x17d742bd4",
      "native_offset" : "0x00000"
   }
,
  {
      "is_managed" : "false",
      "native_address" : "0x1afac34a4",
      "native_offset" : "0x00000"
   }
,
  {
      "is_managed" : "false",
      "native_address" : "0x17d790c70",
      "native_offset" : "0x00000"
   }
,
  {
      "is_managed" : "false",
      "native_address" : "0x17d8394f4",
      "native_offset" : "0x00000"
   }
,
  {
      "is_managed" : "false",
      "native_address" : "0x17d8393a0",
      "native_offset" : "0x00000"
   }
,
  {
      "is_managed" : "false",
      "native_address" : "0x17d8b8cb0",
      "native_offset" : "0x00000"
   }
,
  {
      "is_managed" : "false",
      "native_address" : "0x17d8b8c38",
      "native_offset" : "0x00000"
   }
,
  {
      "is_managed" : "false",
      "native_address" : "0x1afaac26c",
      "native_offset" : "0x00000"
   }
,
  {
      "is_managed" : "false",
      "native_address" : "0x1afaa708c",
      "native_offset" : "0x00000"
   }

  ]
 },
 {
    "is_managed" : false,
    "offset_free_hash" : "0x0",
    "offset_rich_hash" : "0x0",
    "crashed" : false,
    "native_thread_id" : "0x2cfdc7000",
    "thread_info_addr" : "0x2b98bb200",
    "thread_name" : "Thread Pool Worker",
    "ctx" : {
      "IP" : "0x1afa6e904",
      "SP" : "0x2cfdc6db0",
      "BP" : "0x2cfdc6e50"
  },
    "unmanaged_frames" : [
  {
      "is_managed" : "false",
      "native_address" : "0x17d701c4c",
      "native_offset" : "0x00000"
   }
,
  {
      "is_managed" : "false",
      "native_address" : "0x17d838788",
      "native_offset" : "0x00000"
   }
,
  {
      "is_managed" : "false",
      "native_address" : "0x17d838ae4",
      "native_offset" : "0x00000"
   }
,
  {
      "is_managed" : "false",
      "native_address" : "0x17d8388ac",
      "native_offset" : "0x00000"
   }
,
  {
      "is_managed" : "false",
      "native_address" : "0x17d742bd4",
      "native_offset" : "0x00000"
   }
,
  {
      "is_managed" : "false",
      "native_address" : "0x1afac34a4",
      "native_offset" : "0x00000"
   }
,
  {
      "is_managed" : "false",
      "native_address" : "0x17d790c70",
      "native_offset" : "0x00000"
   }
,
  {
      "is_managed" : "false",
      "native_address" : "0x17d8394f4",
      "native_offset" : "0x00000"
   }
,
  {
      "is_managed" : "false",
      "native_address" : "0x17d8393a0",
      "native_offset" : "0x00000"
   }
,
  {
      "is_managed" : "false",
      "native_address" : "0x17d8b8cb0",
      "native_offset" : "0x00000"
   }
,
  {
      "is_managed" : "false",
      "native_address" : "0x17d8b8c38",
      "native_offset" : "0x00000"
   }
,
  {
      "is_managed" : "false",
      "native_address" : "0x1afaac26c",
      "native_offset" : "0x00000"
   }
,
  {
      "is_managed" : "false",
      "native_address" : "0x1afaa708c",
      "native_offset" : "0x00000"
   }

  ]
 },
 {
    "is_managed" : false,
    "offset_free_hash" : "0x0",
    "offset_rich_hash" : "0x0",
    "crashed" : false,
    "native_thread_id" : "0x17df2b000",
    "thread_info_addr" : "0x12e146000",
    "thread_name" : "Finalizer",
    "ctx" : {
      "IP" : "0x1afa6e8ec",
      "SP" : "0x17df2add0",
      "BP" : "0x17df2ae50"
  },
    "unmanaged_frames" : [
  {
      "is_managed" : "false",
      "native_address" : "0x17d701c4c",
      "native_offset" : "0x00000"
   }
,
  {
      "is_managed" : "false",
      "native_address" : "0x17d838788",
      "native_offset" : "0x00000"
   }
,
  {
      "is_managed" : "false",
      "native_address" : "0x17d838ae4",
      "native_offset" : "0x00000"
   }
,
  {
      "is_managed" : "false",
      "native_address" : "0x17d8388ac",
      "native_offset" : "0x00000"
   }
,
  {
      "is_managed" : "false",
      "native_address" : "0x17d742bd4",
      "native_offset" : "0x00000"
   }
,
  {
      "is_managed" : "false",
      "native_address" : "0x1afac34a4",
      "native_offset" : "0x00000"
   }
,
  {
      "is_managed" : "false",
      "native_address" : "0x17d872294",
      "native_offset" : "0x00000"
   }
,
  {
      "is_managed" : "false",
      "native_address" : "0x17d8394f4",
      "native_offset" : "0x00000"
   }
,
  {
      "is_managed" : "false",
      "native_address" : "0x17d8393a0",
      "native_offset" : "0x00000"
   }
,
  {
      "is_managed" : "false",
      "native_address" : "0x17d8b8cb0",
      "native_offset" : "0x00000"
   }
,
  {
      "is_managed" : "false",
      "native_address" : "0x17d8b8c38",
      "native_offset" : "0x00000"
   }
,
  {
      "is_managed" : "false",
      "native_address" : "0x1afaac26c",
      "native_offset" : "0x00000"
   }
,
  {
      "is_managed" : "false",
      "native_address" : "0x1afaa708c",
      "native_offset" : "0x00000"
   }

  ]
 },
 {
    "is_managed" : false,
    "offset_free_hash" : "0x0",
    "offset_rich_hash" : "0x0",
    "crashed" : false,
    "native_thread_id" : "0x2bdf87000",
    "thread_info_addr" : "0x29be0a000",
    "thread_name" : "Thread Pool Worker",
    "ctx" : {
      "IP" : "0x1afa6e904",
      "SP" : "0x2bdf86db0",
      "BP" : "0x2bdf86e50"
  },
    "unmanaged_frames" : [
  {
      "is_managed" : "false",
      "native_address" : "0x17d701c4c",
      "native_offset" : "0x00000"
   }
,
  {
      "is_managed" : "false",
      "native_address" : "0x17d838788",
      "native_offset" : "0x00000"
   }
,
  {
      "is_managed" : "false",
      "native_address" : "0x17d838ae4",
      "native_offset" : "0x00000"
   }
,
  {
      "is_managed" : "false",
      "native_address" : "0x17d8388ac",
      "native_offset" : "0x00000"
   }
,
  {
      "is_managed" : "false",
      "native_address" : "0x17d742bd4",
      "native_offset" : "0x00000"
   }
,
  {
      "is_managed" : "false",
      "native_address" : "0x1afac34a4",
      "native_offset" : "0x00000"
   }
,
  {
      "is_managed" : "false",
      "native_address" : "0x17d790c70",
      "native_offset" : "0x00000"
   }
,
  {
      "is_managed" : "false",
      "native_address" : "0x17d8394f4",
      "native_offset" : "0x00000"
   }
,
  {
      "is_managed" : "false",
      "native_address" : "0x17d8393a0",
      "native_offset" : "0x00000"
   }
,
  {
      "is_managed" : "false",
      "native_address" : "0x17d8b8cb0",
      "native_offset" : "0x00000"
   }
,
  {
      "is_managed" : "false",
      "native_address" : "0x17d8b8c38",
      "native_offset" : "0x00000"
   }
,
  {
      "is_managed" : "false",
      "native_address" : "0x1afaac26c",
      "native_offset" : "0x00000"
   }
,
  {
      "is_managed" : "false",
      "native_address" : "0x1afaa708c",
      "native_offset" : "0x00000"
   }

  ]
 },
 {
    "is_managed" : false,
    "offset_free_hash" : "0x0",
    "offset_rich_hash" : "0x0",
    "crashed" : false,
    "native_thread_id" : "0x2d2cbf000",
    "thread_info_addr" : "0x29bdaf200",
    "thread_name" : "Thread Pool Worker",
    "ctx" : {
      "IP" : "0x1afa6e904",
      "SP" : "0x2d2cbedb0",
      "BP" : "0x2d2cbee50"
  },
    "unmanaged_frames" : [
  {
      "is_managed" : "false",
      "native_address" : "0x17d701c4c",
      "native_offset" : "0x00000"
   }
,
  {
      "is_managed" : "false",
      "native_address" : "0x17d838788",
      "native_offset" : "0x00000"
   }
,
  {
      "is_managed" : "false",
      "native_address" : "0x17d838ae4",
      "native_offset" : "0x00000"
   }
,
  {
      "is_managed" : "false",
      "native_address" : "0x17d8388ac",
      "native_offset" : "0x00000"
   }
,
  {
      "is_managed" : "false",
      "native_address" : "0x17d742bd4",
      "native_offset" : "0x00000"
   }
,
  {
      "is_managed" : "false",
      "native_address" : "0x1afac34a4",
      "native_offset" : "0x00000"
   }
,
  {
      "is_managed" : "false",
      "native_address" : "0x17d790c70",
      "native_offset" : "0x00000"
   }
,
  {
      "is_managed" : "false",
      "native_address" : "0x17d8394f4",
      "native_offset" : "0x00000"
   }
,
  {
      "is_managed" : "false",
      "native_address" : "0x17d8393a0",
      "native_offset" : "0x00000"
   }
,
  {
      "is_managed" : "false",
      "native_address" : "0x17d8b8cb0",
      "native_offset" : "0x00000"
   }
,
  {
      "is_managed" : "false",
      "native_address" : "0x17d8b8c38",
      "native_offset" : "0x00000"
   }
,
  {
      "is_managed" : "false",
      "native_address" : "0x1afaac26c",
      "native_offset" : "0x00000"
   }
,
  {
      "is_managed" : "false",
      "native_address" : "0x1afaa708c",
      "native_offset" : "0x00000"
   }

  ]
 },
 {
    "is_managed" : true,
    "offset_free_hash" : "0xfb24c93e6",
    "offset_rich_hash" : "0xfb24c956f",
    "crashed" : false,
    "native_thread_id" : "0x288c07000",
    "thread_info_addr" : "0x12de2d600",
    "thread_name" : "tid_4b8d7",
    "ctx" : {
      "IP" : "0x1afa72270",
      "SP" : "0x288c06520",
      "BP" : "0x288c065b0"
  },
    "managed_frames" : [
  {
      "is_managed" : "false",
      "native_address" : "unregistered"
   }
,
  {
      "is_managed" : "true",
      "guid" : "612A2C65-AAF8-43D6-98F8-D38B2AD7654A",
      "token" : "0x00000",
      "native_offset" : "0x0",
      "filename" : "mscorlib.dll",
      "sizeofimage" : "0x470000",
      "timestamp" : "0xd0713de6",
      "il_offset" : "0xffffffff"
   }
,
  {
      "is_managed" : "true",
      "guid" : "612A2C65-AAF8-43D6-98F8-D38B2AD7654A",
      "token" : "0x6001f5d",
      "native_offset" : "0x0",
      "filename" : "mscorlib.dll",
      "sizeofimage" : "0x470000",
      "timestamp" : "0xd0713de6",
      "il_offset" : "0x0002f"
   }
,
  {
      "is_managed" : "true",
      "guid" : "612A2C65-AAF8-43D6-98F8-D38B2AD7654A",
      "token" : "0x6001f50",
      "native_offset" : "0x0",
      "filename" : "mscorlib.dll",
      "sizeofimage" : "0x470000",
      "timestamp" : "0xd0713de6",
      "il_offset" : "0x0000e"
   }
,
  {
      "is_managed" : "true",
      "guid" : "612A2C65-AAF8-43D6-98F8-D38B2AD7654A",
      "token" : "0x6001f52",
      "native_offset" : "0x0",
      "filename" : "mscorlib.dll",
      "sizeofimage" : "0x470000",
      "timestamp" : "0xd0713de6",
      "il_offset" : "0x00000"
   }
,
  {
      "is_managed" : "true",
      "guid" : "EB829DFF-9616-411E-83EC-5826A0DB50FA",
      "token" : "0x6005a11",
      "native_offset" : "0x0",
      "filename" : "unityplastic.dll",
      "sizeofimage" : "0x4ec000",
      "timestamp" : "0x62c604f1",
      "il_offset" : "0x00030"
   }
,
  {
      "is_managed" : "true",
      "guid" : "612A2C65-AAF8-43D6-98F8-D38B2AD7654A",
      "token" : "0x6001f7d",
      "native_offset" : "0x0",
      "filename" : "mscorlib.dll",
      "sizeofimage" : "0x470000",
      "timestamp" : "0xd0713de6",
      "il_offset" : "0x00014"
   }
,
  {
      "is_managed" : "true",
      "guid" : "612A2C65-AAF8-43D6-98F8-D38B2AD7654A",
      "token" : "0x6001f25",
      "native_offset" : "0x0",
      "filename" : "mscorlib.dll",
      "sizeofimage" : "0x470000",
      "timestamp" : "0xd0713de6",
      "il_offset" : "0x00071"
   }
,
  {
      "is_managed" : "true",
      "guid" : "612A2C65-AAF8-43D6-98F8-D38B2AD7654A",
      "token" : "0x6001f23",
      "native_offset" : "0x0",
      "filename" : "mscorlib.dll",
      "sizeofimage" : "0x470000",
      "timestamp" : "0xd0713de6",
      "il_offset" : "0x00000"
   }
,
  {
      "is_managed" : "true",
      "guid" : "612A2C65-AAF8-43D6-98F8-D38B2AD7654A",
      "token" : "0x6001f22",
      "native_offset" : "0x0",
      "filename" : "mscorlib.dll",
      "sizeofimage" : "0x470000",
      "timestamp" : "0xd0713de6",
      "il_offset" : "0x0002b"
   }
,
  {
      "is_managed" : "true",
      "guid" : "612A2C65-AAF8-43D6-98F8-D38B2AD7654A",
      "token" : "0x6001f7f",
      "native_offset" : "0x0",
      "filename" : "mscorlib.dll",
      "sizeofimage" : "0x470000",
      "timestamp" : "0xd0713de6",
      "il_offset" : "0x00008"
   }
,
  {
      "is_managed" : "true",
      "guid" : "612A2C65-AAF8-43D6-98F8-D38B2AD7654A",
      "token" : "0x00000",
      "native_offset" : "0x0",
      "filename" : "mscorlib.dll",
      "sizeofimage" : "0x470000",
      "timestamp" : "0xd0713de6",
      "il_offset" : "0x00065"
   }

  ],
  "unmanaged_frames" : [
 {
    "is_managed" : "false",
    "native_address" : "0x17d701c4c",
    "native_offset" : "0x00000"
  }
,
 {
    "is_managed" : "false",
    "native_address" : "0x17d838788",
    "native_offset" : "0x00000"
  }
,
 {
    "is_managed" : "false",
    "native_address" : "0x17d838ae4",
    "native_offset" : "0x00000"
  }
,
 {
    "is_managed" : "false",
    "native_address" : "0x17d8388ac",
    "native_offset" : "0x00000"
  }
,
 {
    "is_managed" : "false",
    "native_address" : "0x17d742bd4",
    "native_offset" : "0x00000"
  }
,
 {
    "is_managed" : "false",
    "native_address" : "0x1afac34a4",
    "native_offset" : "0x00000"
  }
,
 {
    "is_managed" : "false",
    "native_address" : "0x1afaac868",
    "native_offset" : "0x00000"
  }
,
 {
    "is_managed" : "false",
    "native_address" : "0x17d887e08",
    "native_offset" : "0x00000"
  }
,
 {
    "is_managed" : "false",
    "native_address" : "0x17d8444b0",
    "native_offset" : "0x00000"
  }
,
 {
    "is_managed" : "false",
    "native_address" : "0x17d8442e4",
    "native_offset" : "0x00000"
  }
,
 {
    "is_managed" : "false",
    "native_address" : "0x17d8735d8",
    "native_offset" : "0x00000"
  }
,
 {
    "is_managed" : "false",
    "native_address" : "0x17d7dcc8c",
    "native_offset" : "0x00000"
  }
,
 {
    "is_managed" : "true",
    "guid" : "612A2C65-AAF8-43D6-98F8-D38B2AD7654A",
    "token" : "0x00000",
    "native_offset" : "0x0",
    "filename" : "mscorlib.dll",
    "sizeofimage" : "0x470000",
    "timestamp" : "0xd0713de6",
    "il_offset" : "0x00000"
  }
,
 {
    "is_managed" : "true",
    "guid" : "612A2C65-AAF8-43D6-98F8-D38B2AD7654A",
    "token" : "0x6001f5d",
    "native_offset" : "0x0",
    "filename" : "mscorlib.dll",
    "sizeofimage" : "0x470000",
    "timestamp" : "0xd0713de6",
    "il_offset" : "0x00000"
  }
,
 {
    "is_managed" : "true",
    "guid" : "612A2C65-AAF8-43D6-98F8-D38B2AD7654A",
    "token" : "0x6001f50",
    "native_offset" : "0x0",
    "filename" : "mscorlib.dll",
    "sizeofimage" : "0x470000",
    "timestamp" : "0xd0713de6",
    "il_offset" : "0x00000"
  }
,
 {
    "is_managed" : "true",
    "guid" : "612A2C65-AAF8-43D6-98F8-D38B2AD7654A",
    "token" : "0x6001f52",
    "native_offset" : "0x0",
    "filename" : "mscorlib.dll",
    "sizeofimage" : "0x470000",
    "timestamp" : "0xd0713de6",
    "il_offset" : "0x00000"
  }
,
 {
    "is_managed" : "true",
    "guid" : "EB829DFF-9616-411E-83EC-5826A0DB50FA",
    "token" : "0x6005a11",
    "native_offset" : "0x0",
    "filename" : "unityplastic.dll",
    "sizeofimage" : "0x4ec000",
    "timestamp" : "0x62c604f1",
    "il_offset" : "0x00000"
  }
,
 {
    "is_managed" : "true",
    "guid" : "612A2C65-AAF8-43D6-98F8-D38B2AD7654A",
    "token" : "0x6001f7d",
    "native_offset" : "0x0",
    "filename" : "mscorlib.dll",
    "sizeofimage" : "0x470000",
    "timestamp" : "0xd0713de6",
    "il_offset" : "0x00000"
  }
,
 {
    "is_managed" : "true",
    "guid" : "612A2C65-AAF8-43D6-98F8-D38B2AD7654A",
    "token" : "0x6001f25",
    "native_offset" : "0x0",
    "filename" : "mscorlib.dll",
    "sizeofimage" : "0x470000",
    "timestamp" : "0xd0713de6",
    "il_offset" : "0x00000"
  }
,
 {
    "is_managed" : "true",
    "guid" : "612A2C65-AAF8-43D6-98F8-D38B2AD7654A",
    "token" : "0x6001f23",
    "native_offset" : "0x0",
    "filename" : "mscorlib.dll",
    "sizeofimage" : "0x470000",
    "timestamp" : "0xd0713de6",
    "il_offset" : "0x00000"
  }
,
 {
    "is_managed" : "true",
    "guid" : "612A2C65-AAF8-43D6-98F8-D38B2AD7654A",
    "token" : "0x6001f22",
    "native_offset" : "0x0",
    "filename" : "mscorlib.dll",
    "sizeofimage" : "0x470000",
    "timestamp" : "0xd0713de6",
    "il_offset" : "0x00000"
  }
,
 {
    "is_managed" : "true",
    "guid" : "612A2C65-AAF8-43D6-98F8-D38B2AD7654A",
    "token" : "0x6001f7f",
    "native_offset" : "0x0",
    "filename" : "mscorlib.dll",
    "sizeofimage" : "0x470000",
    "timestamp" : "0xd0713de6",
    "il_offset" : "0x00000"
  }
,
 {
    "is_managed" : "true",
    "guid" : "612A2C65-AAF8-43D6-98F8-D38B2AD7654A",
    "token" : "0x00000",
    "native_offset" : "0x0",
    "filename" : "mscorlib.dll",
    "sizeofimage" : "0x470000",
    "timestamp" : "0xd0713de6",
    "il_offset" : "0x00000"
  }
,
 {
    "is_managed" : "false",
    "native_address" : "0x17d6918e0",
    "native_offset" : "0x00000"
  }
,
 {
    "is_managed" : "false",
    "native_address" : "0x17d8176a8",
    "native_offset" : "0x00000"
  }
,
 {
    "is_managed" : "false",
    "native_address" : "0x17d8192a4",
    "native_offset" : "0x00000"
  }
,
 {
    "is_managed" : "false",
    "native_address" : "0x17d8395e8",
    "native_offset" : "0x00000"
  }
,
 {
    "is_managed" : "false",
    "native_address" : "0x17d8393a0",
    "native_offset" : "0x00000"
  }
,
 {
    "is_managed" : "false",
    "native_address" : "0x17d8b8cb0",
    "native_offset" : "0x00000"
  }
,
 {
    "is_managed" : "false",
    "native_address" : "0x17d8b8c38",
    "native_offset" : "0x00000"
  }
,
 {
    "is_managed" : "false",
    "native_address" : "0x1afaac26c",
    "native_offset" : "0x00000"
  }
,
 {
    "is_managed" : "false",
    "native_address" : "0x1afaa708c",
    "native_offset" : "0x00000"
  }

 ]
},
{
  "is_managed" : false,
  "offset_free_hash" : "0x0",
  "offset_rich_hash" : "0x0",
  "crashed" : false,
  "native_thread_id" : "0x2be253000",
  "thread_info_addr" : "0x29cb05200",
  "thread_name" : "Thread Pool I/O Selector",
  "ctx" : {
    "IP" : "0x1afa79598",
    "SP" : "0x2be252ae0",
    "BP" : "0x2be252ce0"
 },
  "unmanaged_frames" : [
 {
    "is_managed" : "false",
    "native_address" : "0x17d701c4c",
    "native_offset" : "0x00000"
  }
,
 {
    "is_managed" : "false",
    "native_address" : "0x17d838788",
    "native_offset" : "0x00000"
  }
,
 {
    "is_managed" : "false",
    "native_address" : "0x17d838ae4",
    "native_offset" : "0x00000"
  }
,
 {
    "is_managed" : "false",
    "native_address" : "0x17d8388ac",
    "native_offset" : "0x00000"
  }
,
 {
    "is_managed" : "false",
    "native_address" : "0x17d742bd4",
    "native_offset" : "0x00000"
  }
,
 {
    "is_managed" : "false",
    "native_address" : "0x1afac34a4",
    "native_offset" : "0x00000"
  }
,
 {
    "is_managed" : "false",
    "native_address" : "0x17d88a8ac",
    "native_offset" : "0x00000"
  }
,
 {
    "is_managed" : "false",
    "native_address" : "0x17d83dcbc",
    "native_offset" : "0x00000"
  }
,
 {
    "is_managed" : "false",
    "native_address" : "0x17d83d6d4",
    "native_offset" : "0x00000"
  }
,
 {
    "is_managed" : "false",
    "native_address" : "0x17d8394f4",
    "native_offset" : "0x00000"
  }
,
 {
    "is_managed" : "false",
    "native_address" : "0x17d8393a0",
    "native_offset" : "0x00000"
  }
,
 {
    "is_managed" : "false",
    "native_address" : "0x17d8b8cb0",
    "native_offset" : "0x00000"
  }
,
 {
    "is_managed" : "false",
    "native_address" : "0x17d8b8c38",
    "native_offset" : "0x00000"
  }
,
 {
    "is_managed" : "false",
    "native_address" : "0x1afaac26c",
    "native_offset" : "0x00000"
  }
,
 {
    "is_managed" : "false",
    "native_address" : "0x1afaa708c",
    "native_offset" : "0x00000"
  }

 ]
},
{
  "is_managed" : false,
  "offset_free_hash" : "0x0",
  "offset_rich_hash" : "0x0",
  "crashed" : false,
  "native_thread_id" : "0x28a51b000",
  "thread_info_addr" : "0x2b9e9e600",
  "thread_name" : "Thread Pool Worker",
  "ctx" : {
    "IP" : "0x1afa6e904",
    "SP" : "0x28a51adb0",
    "BP" : "0x28a51ae50"
 },
  "unmanaged_frames" : [
 {
    "is_managed" : "false",
    "native_address" : "0x17d701c4c",
    "native_offset" : "0x00000"
  }
,
 {
    "is_managed" : "false",
    "native_address" : "0x17d838788",
    "native_offset" : "0x00000"
  }
,
 {
    "is_managed" : "false",
    "native_address" : "0x17d838ae4",
    "native_offset" : "0x00000"
  }
,
 {
    "is_managed" : "false",
    "native_address" : "0x17d8388ac",
    "native_offset" : "0x00000"
  }
,
 {
    "is_managed" : "false",
    "native_address" : "0x17d742bd4",
    "native_offset" : "0x00000"
  }
,
 {
    "is_managed" : "false",
    "native_address" : "0x1afac34a4",
    "native_offset" : "0x00000"
  }
,
 {
    "is_managed" : "false",
    "native_address" : "0x17d790c70",
    "native_offset" : "0x00000"
  }
,
 {
    "is_managed" : "false",
    "native_address" : "0x17d8394f4",
    "native_offset" : "0x00000"
  }
,
 {
    "is_managed" : "false",
    "native_address" : "0x17d8393a0",
    "native_offset" : "0x00000"
  }
,
 {
    "is_managed" : "false",
    "native_address" : "0x17d8b8cb0",
    "native_offset" : "0x00000"
  }
,
 {
    "is_managed" : "false",
    "native_address" : "0x17d8b8c38",
    "native_offset" : "0x00000"
  }
,
 {
    "is_managed" : "false",
    "native_address" : "0x1afaac26c",
    "native_offset" : "0x00000"
  }
,
 {
    "is_managed" : "false",
    "native_address" : "0x1afaa708c",
    "native_offset" : "0x00000"
  }

 ]
},
{
  "is_managed" : false,
  "offset_free_hash" : "0x0",
  "offset_rich_hash" : "0x0",
  "crashed" : false,
  "native_thread_id" : "0x28ddaf000",
  "thread_info_addr" : "0x28c7a5400",
  "thread_name" : "Thread Pool Worker",
  "ctx" : {
    "IP" : "0x1afa6e904",
    "SP" : "0x28ddaedb0",
    "BP" : "0x28ddaee50"
 },
  "unmanaged_frames" : [
 {
    "is_managed" : "false",
    "native_address" : "0x17d701c4c",
    "native_offset" : "0x00000"
  }
,
 {
    "is_managed" : "false",
    "native_address" : "0x17d838788",
    "native_offset" : "0x00000"
  }
,
 {
    "is_managed" : "false",
    "native_address" : "0x17d838ae4",
    "native_offset" : "0x00000"
  }
,
 {
    "is_managed" : "false",
    "native_address" : "0x17d8388ac",
    "native_offset" : "0x00000"
  }
,
 {
    "is_managed" : "false",
    "native_address" : "0x17d742bd4",
    "native_offset" : "0x00000"
  }
,
 {
    "is_managed" : "false",
    "native_address" : "0x1afac34a4",
    "native_offset" : "0x00000"
  }
,
 {
    "is_managed" : "false",
    "native_address" : "0x17d790c70",
    "native_offset" : "0x00000"
  }
,
 {
    "is_managed" : "false",
    "native_address" : "0x17d8394f4",
    "native_offset" : "0x00000"
  }
,
 {
    "is_managed" : "false",
    "native_address" : "0x17d8393a0",
    "native_offset" : "0x00000"
  }
,
 {
    "is_managed" : "false",
    "native_address" : "0x17d8b8cb0",
    "native_offset" : "0x00000"
  }
,
 {
    "is_managed" : "false",
    "native_address" : "0x17d8b8c38",
    "native_offset" : "0x00000"
  }
,
 {
    "is_managed" : "false",
    "native_address" : "0x1afaac26c",
    "native_offset" : "0x00000"
  }
,
 {
    "is_managed" : "false",
    "native_address" : "0x1afaa708c",
    "native_offset" : "0x00000"
  }

 ]
},
{
  "is_managed" : false,
  "offset_free_hash" : "0x0",
  "offset_rich_hash" : "0x0",
  "crashed" : false,
  "native_thread_id" : "0x2cf693000",
  "thread_info_addr" : "0x12e290000",
  "thread_name" : "Thread Pool Worker",
  "ctx" : {
    "IP" : "0x1afa6e904",
    "SP" : "0x2cf692db0",
    "BP" : "0x2cf692e50"
 },
  "unmanaged_frames" : [
 {
    "is_managed" : "false",
    "native_address" : "0x17d701c4c",
    "native_offset" : "0x00000"
  }
,
 {
    "is_managed" : "false",
    "native_address" : "0x17d838788",
    "native_offset" : "0x00000"
  }
,
 {
    "is_managed" : "false",
    "native_address" : "0x17d838ae4",
    "native_offset" : "0x00000"
  }
,
 {
    "is_managed" : "false",
    "native_address" : "0x17d8388ac",
    "native_offset" : "0x00000"
  }
,
 {
    "is_managed" : "false",
    "native_address" : "0x17d742bd4",
    "native_offset" : "0x00000"
  }
,
 {
    "is_managed" : "false",
    "native_address" : "0x1afac34a4",
    "native_offset" : "0x00000"
  }
,
 {
    "is_managed" : "false",
    "native_address" : "0x17d790c70",
    "native_offset" : "0x00000"
  }
,
 {
    "is_managed" : "false",
    "native_address" : "0x17d8394f4",
    "native_offset" : "0x00000"
  }
,
 {
    "is_managed" : "false",
    "native_address" : "0x17d8393a0",
    "native_offset" : "0x00000"
  }
,
 {
    "is_managed" : "false",
    "native_address" : "0x17d8b8cb0",
    "native_offset" : "0x00000"
  }
,
 {
    "is_managed" : "false",
    "native_address" : "0x17d8b8c38",
    "native_offset" : "0x00000"
  }
,
 {
    "is_managed" : "false",
    "native_address" : "0x1afaac26c",
    "native_offset" : "0x00000"
  }
,
 {
    "is_managed" : "false",
    "native_address" : "0x1afaa708c",
    "native_offset" : "0x00000"
  }

 ]
},
{
  "is_managed" : false,
  "offset_free_hash" : "0x0",
  "offset_rich_hash" : "0x0",
  "crashed" : false,
  "native_thread_id" : "0x287463000",
  "thread_info_addr" : "0x287a81e00",
  "thread_name" : "Thread Pool Worker",
  "ctx" : {
    "IP" : "0x1afa6e904",
    "SP" : "0x287462db0",
    "BP" : "0x287462e50"
 },
  "unmanaged_frames" : [
 {
    "is_managed" : "false",
    "native_address" : "0x17d701c4c",
    "native_offset" : "0x00000"
  }
,
 {
    "is_managed" : "false",
    "native_address" : "0x17d838788",
    "native_offset" : "0x00000"
  }
,
 {
    "is_managed" : "false",
    "native_address" : "0x17d838ae4",
    "native_offset" : "0x00000"
  }
,
 {
    "is_managed" : "false",
    "native_address" : "0x17d8388ac",
    "native_offset" : "0x00000"
  }
,
 {
    "is_managed" : "false",
    "native_address" : "0x17d742bd4",
    "native_offset" : "0x00000"
  }
,
 {
    "is_managed" : "false",
    "native_address" : "0x1afac34a4",
    "native_offset" : "0x00000"
  }
,
 {
    "is_managed" : "false",
    "native_address" : "0x17d790c70",
    "native_offset" : "0x00000"
  }
,
 {
    "is_managed" : "false",
    "native_address" : "0x17d8394f4",
    "native_offset" : "0x00000"
  }
,
 {
    "is_managed" : "false",
    "native_address" : "0x17d8393a0",
    "native_offset" : "0x00000"
  }
,
 {
    "is_managed" : "false",
    "native_address" : "0x17d8b8cb0",
    "native_offset" : "0x00000"
  }
,
 {
    "is_managed" : "false",
    "native_address" : "0x17d8b8c38",
    "native_offset" : "0x00000"
  }
,
 {
    "is_managed" : "false",
    "native_address" : "0x1afaac26c",
    "native_offset" : "0x00000"
  }
,
 {
    "is_managed" : "false",
    "native_address" : "0x1afaa708c",
    "native_offset" : "0x00000"
  }

 ]
},
{
  "is_managed" : false,
  "offset_free_hash" : "0x0",
  "offset_rich_hash" : "0x0",
  "crashed" : false,
  "native_thread_id" : "0x282a87000",
  "thread_info_addr" : "0x2913bf400",
  "thread_name" : "Thread Pool Worker",
  "ctx" : {
    "IP" : "0x1afa6e904",
    "SP" : "0x282a86db0",
    "BP" : "0x282a86e50"
 },
  "unmanaged_frames" : [
 {
    "is_managed" : "false",
    "native_address" : "0x17d701c4c",
    "native_offset" : "0x00000"
  }
,
 {
    "is_managed" : "false",
    "native_address" : "0x17d838788",
    "native_offset" : "0x00000"
  }
,
 {
    "is_managed" : "false",
    "native_address" : "0x17d838ae4",
    "native_offset" : "0x00000"
  }
,
 {
    "is_managed" : "false",
    "native_address" : "0x17d8388ac",
    "native_offset" : "0x00000"
  }
,
 {
    "is_managed" : "false",
    "native_address" : "0x17d742bd4",
    "native_offset" : "0x00000"
  }
,
 {
    "is_managed" : "false",
    "native_address" : "0x1afac34a4",
    "native_offset" : "0x00000"
  }
,
 {
    "is_managed" : "false",
    "native_address" : "0x17d790c70",
    "native_offset" : "0x00000"
  }
,
 {
    "is_managed" : "false",
    "native_address" : "0x17d8394f4",
    "native_offset" : "0x00000"
  }
,
 {
    "is_managed" : "false",
    "native_address" : "0x17d8393a0",
    "native_offset" : "0x00000"
  }
,
 {
    "is_managed" : "false",
    "native_address" : "0x17d8b8cb0",
    "native_offset" : "0x00000"
  }
,
 {
    "is_managed" : "false",
    "native_address" : "0x17d8b8c38",
    "native_offset" : "0x00000"
  }
,
 {
    "is_managed" : "false",
    "native_address" : "0x1afaac26c",
    "native_offset" : "0x00000"
  }
,
 {
    "is_managed" : "false",
    "native_address" : "0x1afaa708c",
    "native_offset" : "0x00000"
  }

 ]
},
{
  "is_managed" : true,
  "offset_free_hash" : "0xa569772a0",
  "offset_rich_hash" : "0xa5697763a",
  "crashed" : true,
  "native_thread_id" : "0x10a9f4580",
  "thread_info_addr" : "0x12ce6de00",
  "thread_name" : "tid_103",
  "ctx" : {
    "IP" : "0x105642c28",
    "SP" : "0x16b1eb6a0",
    "BP" : "0x16b1eb6b0"
 },
  "managed_frames" : [
 {
    "is_managed" : "false",
    "native_address" : "unregistered"
  }
,
 {
    "is_managed" : "true",
    "guid" : "10F522B7-3746-4037-B248-E9A3C3BD7C67",
    "token" : "0x00000",
    "native_offset" : "0x0",
    "filename" : "UnityEditor.CoreModule.dll",
    "sizeofimage" : "0x81a000",
    "timestamp" : "0x97e985a9",
    "il_offset" : "0xffffffff"
  }
,
 {
    "is_managed" : "true",
    "guid" : "10F522B7-3746-4037-B248-E9A3C3BD7C67",
    "token" : "0x6007ed4",
    "native_offset" : "0x0",
    "filename" : "UnityEditor.CoreModule.dll",
    "sizeofimage" : "0x81a000",
    "timestamp" : "0x97e985a9",
    "il_offset" : "0x00001"
  }
,
 {
    "is_managed" : "true",
    "guid" : "10F522B7-3746-4037-B248-E9A3C3BD7C67",
    "token" : "0x6007f3b",
    "native_offset" : "0x0",
    "filename" : "UnityEditor.CoreModule.dll",
    "sizeofimage" : "0x81a000",
    "timestamp" : "0x97e985a9",
    "il_offset" : "0x00317"
  }
,
 {
    "is_managed" : "true",
    "guid" : "10F522B7-3746-4037-B248-E9A3C3BD7C67",
    "token" : "0x6007dcf",
    "native_offset" : "0x0",
    "filename" : "UnityEditor.CoreModule.dll",
    "sizeofimage" : "0x81a000",
    "timestamp" : "0x97e985a9",
    "il_offset" : "0x0000e"
  }
,
 {
    "is_managed" : "true",
    "guid" : "10F522B7-3746-4037-B248-E9A3C3BD7C67",
    "token" : "0x6007db9",
    "native_offset" : "0x0",
    "filename" : "UnityEditor.CoreModule.dll",
    "sizeofimage" : "0x81a000",
    "timestamp" : "0x97e985a9",
    "il_offset" : "0x00041"
  }
,
 {
    "is_managed" : "true",
    "guid" : "10F522B7-3746-4037-B248-E9A3C3BD7C67",
    "token" : "0x6001f4a",
    "native_offset" : "0x0",
    "filename" : "UnityEditor.CoreModule.dll",
    "sizeofimage" : "0x81a000",
    "timestamp" : "0x97e985a9",
    "il_offset" : "0x0000a"
  }
,
 {
    "is_managed" : "true",
    "guid" : "612A2C65-AAF8-43D6-98F8-D38B2AD7654A",
    "token" : "0x00000",
    "native_offset" : "0x0",
    "filename" : "mscorlib.dll",
    "sizeofimage" : "0x470000",
    "timestamp" : "0xd0713de6",
    "il_offset" : "0x0002a"
  }

 ],
"unmanaged_frames" : [
{
  "is_managed" : "false",
  "native_address" : "0x17d701c4c",
  "native_offset" : "0x00000"
 }
,
{
  "is_managed" : "false",
  "native_address" : "0x17d838788",
  "native_offset" : "0x00000"
 }
,
{
  "is_managed" : "false",
  "native_address" : "0x17d838ae4",
  "native_offset" : "0x00000"
 }
,
{
  "is_managed" : "false",
  "native_address" : "0x17d8390d4",
  "native_offset" : "0x00000"
 }
,
{
  "is_managed" : "false",
  "native_address" : "0x17d743a20",
  "native_offset" : "0x00000"
 }
,
{
  "is_managed" : "false",
  "native_address" : "0x17d705d58",
  "native_offset" : "0x00000"
 }
,
{
  "is_managed" : "false",
  "native_address" : "0x17d68e620",
  "native_offset" : "0x00000"
 }
,
{
  "is_managed" : "false",
  "native_address" : "0x1afac34a4",
  "native_offset" : "0x00000"
 }
,
{
  "is_managed" : "false",
  "native_address" : "0x10535d8f0",
  "native_offset" : "0x00000"
 }
,
{
  "is_managed" : "false",
  "native_address" : "0x10535d8f0",
  "native_offset" : "0x00000"
 }
,
{
  "is_managed" : "false",
  "native_address" : "0x105340fd0",
  "native_offset" : "0x00000"
 }
,
{
  "is_managed" : "false",
  "native_address" : "0x10534169c",
  "native_offset" : "0x00000"
 }
,
{
  "is_managed" : "false",
  "native_address" : "0x1051ac6a4",
  "native_offset" : "0x00000"
 }
,
{
  "is_managed" : "false",
  "native_address" : "0x1051ac5f0",
  "native_offset" : "0x00000"
 }
,
{
  "is_managed" : "false",
  "native_address" : "0x1051ac1c8",
  "native_offset" : "0x00000"
 }
,
{
  "is_managed" : "false",
  "native_address" : "0x1051ad224",
  "native_offset" : "0x00000"
 }
,
{
  "is_managed" : "false",
  "native_address" : "0x1054c0a58",
  "native_offset" : "0x00000"
 }
,
{
  "is_managed" : "false",
  "native_address" : "0x1054bdd90",
  "native_offset" : "0x00000"
 }
,
{
  "is_managed" : "false",
  "native_address" : "0x10645000c",
  "native_offset" : "0x00000"
 }
,
{
  "is_managed" : "false",
  "native_address" : "0x106456a44",
  "native_offset" : "0x00000"
 }
,
{
  "is_managed" : "false",
  "native_address" : "0x106457240",
  "native_offset" : "0x00000"
 }
,
{
  "is_managed" : "false",
  "native_address" : "0x1066c993c",
  "native_offset" : "0x00000"
 }
,
{
  "is_managed" : "false",
  "native_address" : "0x1061c93dc",
  "native_offset" : "0x00000"
 }
,
{
  "is_managed" : "false",
  "native_address" : "0x104f87b28",
  "native_offset" : "0x00000"
 }
,
{
  "is_managed" : "true",
  "guid" : "10F522B7-3746-4037-B248-E9A3C3BD7C67",
  "token" : "0x00000",
  "native_offset" : "0x0",
  "filename" : "UnityEditor.CoreModule.dll",
  "sizeofimage" : "0x81a000",
  "timestamp" : "0x97e985a9",
  "il_offset" : "0x00000"
 }
,
{
  "is_managed" : "true",
  "guid" : "10F522B7-3746-4037-B248-E9A3C3BD7C67",
  "token" : "0x6007ed4",
  "native_offset" : "0x0",
  "filename" : "UnityEditor.CoreModule.dll",
  "sizeofimage" : "0x81a000",
  "timestamp" : "0x97e985a9",
  "il_offset" : "0x00000"
 }
,
{
  "is_managed" : "true",
  "guid" : "10F522B7-3746-4037-B248-E9A3C3BD7C67",
  "token" : "0x6007f3b",
  "native_offset" : "0x0",
  "filename" : "UnityEditor.CoreModule.dll",
  "sizeofimage" : "0x81a000",
  "timestamp" : "0x97e985a9",
  "il_offset" : "0x00000"
 }
,
{
  "is_managed" : "true",
  "guid" : "10F522B7-3746-4037-B248-E9A3C3BD7C67",
  "token" : "0x6007dcf",
  "native_offset" : "0x0",
  "filename" : "UnityEditor.CoreModule.dll",
  "sizeofimage" : "0x81a000",
  "timestamp" : "0x97e985a9",
  "il_offset" : "0x00000"
 }
,
{
  "is_managed" : "true",
  "guid" : "10F522B7-3746-4037-B248-E9A3C3BD7C67",
  "token" : "0x6007db9",
  "native_offset" : "0x0",
  "filename" : "UnityEditor.CoreModule.dll",
  "sizeofimage" : "0x81a000",
  "timestamp" : "0x97e985a9",
  "il_offset" : "0x00000"
 }
,
{
  "is_managed" : "true",
  "guid" : "10F522B7-3746-4037-B248-E9A3C3BD7C67",
  "token" : "0x6001f4a",
  "native_offset" : "0x0",
  "filename" : "UnityEditor.CoreModule.dll",
  "sizeofimage" : "0x81a000",
  "timestamp" : "0x97e985a9",
  "il_offset" : "0x00000"
 }
,
{
  "is_managed" : "true",
  "guid" : "612A2C65-AAF8-43D6-98F8-D38B2AD7654A",
  "token" : "0x00000",
  "native_offset" : "0x0",
  "filename" : "mscorlib.dll",
  "sizeofimage" : "0x470000",
  "timestamp" : "0xd0713de6",
  "il_offset" : "0x00000"
 }
,
{
  "is_managed" : "false",
  "native_address" : "0x17d6918e0",
  "native_offset" : "0x00000"
 }
,
{
  "is_managed" : "false",
  "native_address" : "0x17d8176a8",
  "native_offset" : "0x00000"
 }
,
{
  "is_managed" : "false",
  "native_address" : "0x17d8175c8",
  "native_offset" : "0x00000"
 }
,
{
  "is_managed" : "false",
  "native_address" : "0x105864a44",
  "native_offset" : "0x00000"
 }
,
{
  "is_managed" : "false",
  "native_address" : "0x10584287c",
  "native_offset" : "0x00000"
 }
,
{
  "is_managed" : "false",
  "native_address" : "0x10596f578",
  "native_offset" : "0x00000"
 }
,
{
  "is_managed" : "false",
  "native_address" : "0x1062d2eb8",
  "native_offset" : "0x00000"
 }
,
{
  "is_managed" : "false",
  "native_address" : "0x1074b578c",
  "native_offset" : "0x00000"
 }
,
{
  "is_managed" : "false",
  "native_address" : "0x1071f1738",
  "native_offset" : "0x00000"
 }
,
{
  "is_managed" : "false",
  "native_address" : "0x1071f1a8c",
  "native_offset" : "0x00000"
 }
,
{
  "is_managed" : "false",
  "native_address" : "0x1071f1874",
  "native_offset" : "0x00000"
 }
,
{
  "is_managed" : "false",
  "native_address" : "0x1074b5668",
  "native_offset" : "0x00000"
 }
,
{
  "is_managed" : "false",
  "native_address" : "0x1074affc4",
  "native_offset" : "0x00000"
 }
,
{
  "is_managed" : "false",
  "native_address" : "0x1074b0118",
  "native_offset" : "0x00000"
 }
,
{
  "is_managed" : "false",
  "native_address" : "0x1b2e4e1fc",
  "native_offset" : "0x00000"
 }
,
{
  "is_managed" : "false",
  "native_address" : "0x1b284ce6c",
  "native_offset" : "0x00000"
 }
,
{
  "is_managed" : "false",
  "native_address" : "0x1074a0fd4",
  "native_offset" : "0x00000"
 }
,
{
  "is_managed" : "false",
  "native_address" : "0x1074a4398",
  "native_offset" : "0x00000"
 }
,
{
  "is_managed" : "false",
  "native_address" : "0x1b0a9e920",
  "native_offset" : "0x00000"
 }
,
{
  "is_managed" : "false",
  "native_address" : "0x1afb93964",
  "native_offset" : "0x00000"
 }
,
{
  "is_managed" : "false",
  "native_address" : "0x1afb9354c",
  "native_offset" : "0x00000"
 }
,
{
  "is_managed" : "false",
  "native_address" : "0x1afb92fd4",
  "native_offset" : "0x00000"
 }
,
{
  "is_managed" : "false",
  "native_address" : "0x1afb77a64",
  "native_offset" : "0x00000"
 }
,
{
  "is_managed" : "false",
  "native_address" : "0x1afb76b34",
  "native_offset" : "0x00000"
 }
,
{
  "is_managed" : "false",
  "native_address" : "0x1b87b6338",
  "native_offset" : "0x00000"
 }
,
{
  "is_managed" : "false",
  "native_address" : "0x1b87b5fc4",
  "native_offset" : "0x00000"
 }
,
{
  "is_managed" : "false",
  "native_address" : "0x1b87b5e68",
  "native_offset" : "0x00000"
 }
,
{
  "is_managed" : "false",
  "native_address" : "0x1b26de51c",
  "native_offset" : "0x00000"
 }
,
{
  "is_managed" : "false",
  "native_address" : "0x1b26dce14",
  "native_offset" : "0x00000"
 }
,
{
  "is_managed" : "false",
  "native_address" : "0x1b26cefe0",
  "native_offset" : "0x00000"
 }
,
{
  "is_managed" : "false",
  "native_address" : "0x1b26a06fc",
  "native_offset" : "0x00000"
 }
,
{
  "is_managed" : "false",
  "native_address" : "0x1074a16e8",
  "native_offset" : "0x00000"
 }
,
{
  "is_managed" : "false",
  "native_address" : "0x1074a1a20",
  "native_offset" : "0x00000"
 }
,
{
  "is_managed" : "false",
  "native_address" : "0x10a98108c",
  "native_offset" : "0x00000"
 }

]
},
{
"is_managed" : false,
"offset_free_hash" : "0x0",
"offset_rich_hash" : "0x0",
"crashed" : false,
"native_thread_id" : "0x17e137000",
"thread_info_addr" : "0x12e149200",
"thread_name" : "Debugger agent",
"ctx" : {
  "IP" : "0x1afa76e84",
  "SP" : "0x17e136aa0",
  "BP" : "0x17e136ae0"
},
"unmanaged_frames" : [
{
  "is_managed" : "false",
  "native_address" : "0x17d701c4c",
  "native_offset" : "0x00000"
 }
,
{
  "is_managed" : "false",
  "native_address" : "0x17d838788",
  "native_offset" : "0x00000"
 }
,
{
  "is_managed" : "false",
  "native_address" : "0x17d838ae4",
  "native_offset" : "0x00000"
 }
,
{
  "is_managed" : "false",
  "native_address" : "0x17d8388ac",
  "native_offset" : "0x00000"
 }
,
{
  "is_managed" : "false",
  "native_address" : "0x17d742bd4",
  "native_offset" : "0x00000"
 }
,
{
  "is_managed" : "false",
  "native_address" : "0x1afac34a4",
  "native_offset" : "0x00000"
 }
,
{
  "is_managed" : "false",
  "native_address" : "0x17d7783e0",
  "native_offset" : "0x00000"
 }
,
{
  "is_managed" : "false",
  "native_address" : "0x17d76f760",
  "native_offset" : "0x00000"
 }
,
{
  "is_managed" : "false",
  "native_address" : "0x17d8394f4",
  "native_offset" : "0x00000"
 }
,
{
  "is_managed" : "false",
  "native_address" : "0x17d8393a0",
  "native_offset" : "0x00000"
 }
,
{
  "is_managed" : "false",
  "native_address" : "0x17d8b8cb0",
  "native_offset" : "0x00000"
 }
,
{
  "is_managed" : "false",
  "native_address" : "0x17d8b8c38",
  "native_offset" : "0x00000"
 }
,
{
  "is_managed" : "false",
  "native_address" : "0x1afaac26c",
  "native_offset" : "0x00000"
 }
,
{
  "is_managed" : "false",
  "native_address" : "0x1afaa708c",
  "native_offset" : "0x00000"
 }

]
}
]
}